text_cleanser/__init__.py
text_cleanser/utils.py
puctuation_and_stopwords_remover-0.1.1.dist-info/METADATA
puctuation_and_stopwords_remover-0.1.1.dist-info/WHEEL
puctuation_and_stopwords_remover-0.1.1.dist-info/top_level.txt
puctuation_and_stopwords_remover-0.1.1.dist-info/RECORD
