Metadata-Version: 2.1
Name: puctuation_and_stopwords_remover
Version: 0.1.1
Summary: A Python package for data cleaning process of NLP tasks, specifically for removing punctuation and stopwords.
Home-page: https://github.com/RMWajahat/tpsc
Author: Muhammad Wajahat Hussain
Author-email: rajawajahat@example.com
Requires-Python: >=3.6
Requires-Dist: nltk
